scruby_plugin/__init__.py
scruby_plugin/plugin.py
scruby_plugin/py.typed
scruby_plugin-0.4.5.dist-info/licenses/LICENSE
scruby_plugin-0.4.5.dist-info/WHEEL
scruby_plugin-0.4.5.dist-info/METADATA
scruby_plugin-0.4.5.dist-info/RECORD
