Metadata-Version: 2.4
Name: scruby-plugin
Version: 0.4.5
Summary: Library for creating Scruby plugins.
Keywords: scruby,create,plugin,database
Author: kebasyaty
Author-email: kebasyaty <kebasyaty@gmail.com>
License-Expression: MIT
License-File: LICENSE
Classifier: Development Status :: 5 - Production/Stable
Classifier: Intended Audience :: Developers
Classifier: License :: OSI Approved :: MIT License
Classifier: Operating System :: MacOS :: MacOS X
Classifier: Operating System :: Microsoft :: Windows
Classifier: Operating System :: POSIX
Classifier: Operating System :: POSIX :: Linux
Classifier: Programming Language :: Python :: 3
Classifier: Programming Language :: Python :: 3 :: Only
Classifier: Programming Language :: Python :: 3.12
Classifier: Programming Language :: Python :: 3.13
Classifier: Programming Language :: Python :: 3.14
Classifier: Programming Language :: Python :: Implementation :: CPython
Classifier: Topic :: Software Development :: Libraries
Classifier: Topic :: Software Development :: Libraries :: Python Modules
Classifier: Topic :: Database
Classifier: Typing :: Typed
Requires-Python: >=3.12, <4.0
Project-URL: Bug Tracker, https://github.com/kebasyaty/scruby-plugin/issues
Project-URL: Changelog, https://github.com/kebasyaty/scruby-plugin/blob/v0/CHANGELOG.md
Project-URL: Homepage, https://github.com/kebasyaty/scruby-plugin
Project-URL: Repository, https://github.com/kebasyaty/scruby-plugin
Project-URL: Source, https://github.com/kebasyaty/scruby-plugin
